CHANGES.md
LICENSE
MANIFEST.in
Makefile
README.md
RELEASING.md
setup.cfg
setup.py
pdvega/__init__.py
pdvega/_axes.py
pdvega/_core.py
pdvega/_pandas_internals.py
pdvega/_utils.py
pdvega/plotting.py
pdvega/schema.py
pdvega/vega-lite-v2.0.4.json
pdvega.egg-info/PKG-INFO
pdvega.egg-info/SOURCES.txt
pdvega.egg-info/dependency_links.txt
pdvega.egg-info/requires.txt
pdvega.egg-info/top_level.txt
pdvega/tests/__init__.py
pdvega/tests/test_core.py
pdvega/tests/test_core_common.py
pdvega/tests/test_plotting.py
pdvega/tests/test_utils.py
pdvega/tests/utils.py