Metadata-Version: 1.1
Name: pdvega
Version: 0.1
Summary: Pandas plotting interface to Vega and Vega-Lite
Home-page: http://jakevdp.github.io/pdvega/
Author: Jake VanderPlas
Author-email: jakevdp@gmail.com
License: MIT
Download-URL: http://github.com/jakevdp/pdvega/
Platform: UNKNOWN
Classifier: Development Status :: 4 - Beta
Classifier: Environment :: Console
Classifier: Intended Audience :: Science/Research
Classifier: License :: OSI Approved :: BSD License
Classifier: Natural Language :: English
Classifier: Programming Language :: Python :: 2.7
Classifier: Programming Language :: Python :: 3.5
Classifier: Programming Language :: Python :: 3.6
